main.py
mseep_cryptopanic_mcp_server-0.1.4.dist-info/licenses/LICENSE
mseep_cryptopanic_mcp_server-0.1.4.dist-info/METADATA
mseep_cryptopanic_mcp_server-0.1.4.dist-info/WHEEL
mseep_cryptopanic_mcp_server-0.1.4.dist-info/entry_points.txt
mseep_cryptopanic_mcp_server-0.1.4.dist-info/top_level.txt
mseep_cryptopanic_mcp_server-0.1.4.dist-info/RECORD
